Metadata-Version: 2.4
Name: aided
Version: 0.3.1
Summary: Analysis and Investigation of the Dynamic Electron Density
Author: J. Robert Michael, PhD
Maintainer: J. Robert Michael, PhD
License-Expression: MIT
Project-URL: Homepage, https://github.com/drjrm3/aided
Project-URL: Source, https://github.com/drjrm3/aided
Requires-Python: >=3.10
License-File: LICENSE
Requires-Dist: numpy==1.26.4
Requires-Dist: scipy==1.13.0
Dynamic: license-file
